README.rst
setup.py
stormbot_quote/__init__.py
stormbot_quote.egg-info/PKG-INFO
stormbot_quote.egg-info/SOURCES.txt
stormbot_quote.egg-info/dependency_links.txt
stormbot_quote.egg-info/entry_points.txt
stormbot_quote.egg-info/requires.txt
stormbot_quote.egg-info/top_level.txt