Metadata-Version: 1.1
Name: stormbot-quote
Version: 2.0b1
Summary: store best quote easily from your Stormbot
Home-page: https://github.com/manoir/stormbot-quote
Author: Paul Fariello
Author-email: paul@fariello.eu
License: UNKNOWN
Platform: UNKNOWN
Classifier: Environment :: Console
Classifier: Operating System :: POSIX
Classifier: Topic :: Communications :: Chat
Classifier: Programming Language :: Python
